chenguolibs/__init__.py
chenguolibs/chenguolibs.py
chenguolibs-2.1.0.dist-info/LICENSE
chenguolibs-2.1.0.dist-info/METADATA
chenguolibs-2.1.0.dist-info/WHEEL
chenguolibs-2.1.0.dist-info/top_level.txt
chenguolibs-2.1.0.dist-info/RECORD
